automutualinformation/__init__.py
automutualinformation/test.py
automutualinformation/mi/grassberger.py
automutualinformation/mi/sequential_mi.py
automutualinformation/modelfitting/comparison.py
automutualinformation/modelfitting/decay_functions.py
automutualinformation/modelfitting/fit.py
automutualinformation-0.1.5.dist-info/LICENSE
automutualinformation-0.1.5.dist-info/METADATA
automutualinformation-0.1.5.dist-info/WHEEL
automutualinformation-0.1.5.dist-info/top_level.txt
automutualinformation-0.1.5.dist-info/RECORD
