Metadata-Version: 2.1
Name: automutualinformation
Version: 0.1.5
Summary: Auto Mutual Information (Sequential Mutual Information) for temporal data.
Home-page: https://github.com/timsainb/automutualinformation
Author: Tim Sainburg
License: MIT
Platform: UNKNOWN
License-File: LICENSE
Requires-Dist: numpy
Requires-Dist: scipy
Requires-Dist: tqdm
Requires-Dist: scikit-learn
Requires-Dist: joblib
Requires-Dist: matplotlib
Requires-Dist: colorednoise
Requires-Dist: pandas
Requires-Dist: lmfit
